NCP_CFR/CFR.py
NCP_CFR/__init__.py
NCP_CFR-0.14.dist-info/DESCRIPTION.rst
NCP_CFR-0.14.dist-info/METADATA
NCP_CFR-0.14.dist-info/RECORD
NCP_CFR-0.14.dist-info/WHEEL
NCP_CFR-0.14.dist-info/metadata.json
NCP_CFR-0.14.dist-info/top_level.txt
