Metadata-Version: 2.0
Name: NCP-CFR
Version: 0.14
Summary: This is for CFR(Clova Face Recognition) service of NAVER Cloud Platform
Home-page: https://github.com/ultimatelife/NCP_CFR.git
Author: geonwoo.kim
Author-email: drama0708@gmail.com
License: Naver Cloud Platform
Keywords: NCP,CFR,Clova,clova
Platform: UNKNOWN
Classifier: Programming Language :: Python :: 3.6
Requires-Python: >=3.6
Requires-Dist: requests (>=2.17.3)
